pypass/__init__.py
pypass/makepass.py
pypass/generator/__init__.py
pypass/generator/diceware.py
pypass/generator/diceware.sqlite
pypass/passphrase/__init__.py
pypass/passphrase/transform.py
pypass_generator-0.2.dist-info/DESCRIPTION.rst
pypass_generator-0.2.dist-info/METADATA
pypass_generator-0.2.dist-info/RECORD
pypass_generator-0.2.dist-info/WHEEL
pypass_generator-0.2.dist-info/metadata.json
pypass_generator-0.2.dist-info/top_level.txt
