Metadata-Version: 2.0
Name: pypass-generator
Version: 0.2
Summary: Password and Passphrase Generator using Diceware and other sources
Home-page: https://bitbucket.org/darrenpmeyer/pypass-generator
Author: Darren P Meyer
Author-email: darren@darrenpmeyer.com
License: License :: OSI Approved :: Apache Software License
Platform: UNKNOWN
Requires-Dist: requests (>=2.12.5)
